{
  "$schema": "https://json.schemastore.org/tsconfig",
  "compilerOptions": {
    "module": "Node16",
    "moduleResolution": "node16",
    "rootDir": "./src/",
    "outDir": "./dist/",
    "strict": true,
    "importHelpers": true,
    "experimentalDecorators": true,
    "esModuleInterop": true,
    "skipLibCheck": true,
    "allowSyntheticDefaultImports": true,
    "forceConsistentCasingInFileNames": true,
    "removeComments": true,
    "typeRoots": [
      "node_modules/@types"
    ],
    "sourceMap": true,
    "baseUrl": "./"
  },
  "ts-node": {
    "transpileOnly": true,
    "files": true,
    "experimentalResolver": true
  }
}
